gocept.amqprun-3.0-py3.7-nspkg.pth
gocept/amqprun/__init__.py
gocept/amqprun/amqp.xml
gocept/amqprun/handler.py
gocept/amqprun/interfaces.py
gocept/amqprun/main.py
gocept/amqprun/message.py
gocept/amqprun/readfiles.py
gocept/amqprun/schema.xml
gocept/amqprun/server.py
gocept/amqprun/session.py
gocept/amqprun/settings.py
gocept/amqprun/testing.py
gocept/amqprun/worker.py
gocept/amqprun/tests/__init__.py
gocept/amqprun/tests/basic.conf
gocept/amqprun/tests/basic.py
gocept/amqprun/tests/basic.zcml
gocept/amqprun/tests/filestore.conf
gocept/amqprun/tests/integration.conf
gocept/amqprun/tests/integration.py
gocept/amqprun/tests/integration.zcml
gocept/amqprun/tests/logging.conf
gocept/amqprun/tests/logging.zcml
gocept/amqprun/tests/process.conf
gocept/amqprun/tests/process.zcml
gocept/amqprun/tests/readfiles-error.conf
gocept/amqprun/tests/readfiles-error.zcml
gocept/amqprun/tests/readfiles.conf
gocept/amqprun/tests/readfiles.zcml
gocept/amqprun/tests/server.conf
gocept/amqprun/tests/server.zcml
gocept/amqprun/tests/settings.conf
gocept/amqprun/tests/settings.zcml
gocept/amqprun/tests/test_handler.py
gocept/amqprun/tests/test_main.py
gocept/amqprun/tests/test_message.py
gocept/amqprun/tests/test_readfiles.py
gocept/amqprun/tests/test_sender.py
gocept/amqprun/tests/test_server.py
gocept/amqprun/tests/test_session.py
gocept/amqprun/tests/test_worker.py
gocept.amqprun-3.0.dist-info/LICENSE.txt
gocept.amqprun-3.0.dist-info/METADATA
gocept.amqprun-3.0.dist-info/WHEEL
gocept.amqprun-3.0.dist-info/entry_points.txt
gocept.amqprun-3.0.dist-info/namespace_packages.txt
gocept.amqprun-3.0.dist-info/top_level.txt
gocept.amqprun-3.0.dist-info/RECORD
