Metadata-Version: 2.1
Name: gocept.amqprun
Version: 3.0
Summary: gocept.amqprun helps you writing and running AMQP consumers, and sending AMQP messages. It currently only supports AMQP 0-9-1 and integrates with the Zope Tool Kit (ZTK) so you can use adapters, utilities and all the buzz.
Home-page: https://github.com/NativeInstruments/gocept.amqprun
Author: gocept <mail at gocept dot com>
Author-email: mail@gocept.com
License: ZPL
Platform: UNKNOWN
Classifier: Development Status :: 4 - Beta
Classifier: Environment :: Console
Classifier: Framework :: Zope :: 3
Classifier: Intended Audience :: Developers
Classifier: License :: OSI Approved :: Zope Public License
Classifier: License :: OSI Approved
Classifier: Natural Language :: English
Classifier: Operating System :: OS Independent
Classifier: Programming Language :: Python :: 3
Classifier: Programming Language :: Python :: 3.7
Classifier: Programming Language :: Python :: 3.8
Classifier: Programming Language :: Python :: 3.9
Classifier: Programming Language :: Python :: 3 :: Only
Classifier: Programming Language :: Python :: Implementation :: CPython
Classifier: Programming Language :: Python
Classifier: Topic :: Software Development :: Libraries :: Application Frameworks
Classifier: Topic :: Software Development
Requires-Python: >=3.7, <4
Requires-Dist: ZConfig
Requires-Dist: kombu
Requires-Dist: setuptools
Requires-Dist: transaction
Requires-Dist: zope.component[zcml]
Requires-Dist: zope.configuration
Requires-Dist: zope.event
Requires-Dist: zope.interface
Requires-Dist: zope.schema
Provides-Extra: readfiles
Requires-Dist: gocept.filestore ; extra == 'readfiles'
Provides-Extra: security
Requires-Dist: zope.security (>=4.0.0dev) ; extra == 'security'
Provides-Extra: test
Requires-Dist: amqp ; extra == 'test'
Requires-Dist: gocept.filestore ; extra == 'test'
Requires-Dist: zope.security (>=4.0.0dev) ; extra == 'test'
Requires-Dist: gocept.testing ; extra == 'test'
Requires-Dist: plone.testing ; extra == 'test'
Requires-Dist: pytest ; extra == 'test'
Requires-Dist: zope.testing ; extra == 'test'
Provides-Extra: testing
Requires-Dist: amqp ; extra == 'testing'
